git_pilot-0.2.0.dist-info/licenses/LICENSE
src/__init__.py
src/main.py
src/cli/__init__.py
src/cli/commands.py
src/cli/parsers.py
src/config/__init__.py
src/config/loader.py
src/core/__init__.py
src/core/comparator.py
src/core/farcade.py
src/core/init.py
src/core/interfaces.py
src/core/sync_engine.py
src/diff/__init__.py
src/diff/generator.py
src/diff/interactive.py
src/providers/__init__.py
src/providers/base.py
src/providers/github.py
src/state/__init__.py
src/state/file_state.py
src/template_engine/__init__.py
src/template_engine/jinja_loader.py
src/utils/__init__.py
src/utils/hash.py
src/utils/logger.py
git_pilot-0.2.0.dist-info/METADATA
git_pilot-0.2.0.dist-info/WHEEL
git_pilot-0.2.0.dist-info/entry_points.txt
git_pilot-0.2.0.dist-info/top_level.txt
git_pilot-0.2.0.dist-info/RECORD
