Metadata-Version: 2.4
Name: git-pilot
Version: 0.2.0
Summary: A CLI tool to sync and update Git workflows and configurations across multiple repositories efficiently and consistently.
Author: r3d-shadow
License: Apache License 2.0
Classifier: Environment :: Console
Classifier: Intended Audience :: Developers
Classifier: Programming Language :: Python :: 3.10
Classifier: Programming Language :: Python :: 3.11
Classifier: Programming Language :: Python :: 3.12
Classifier: Topic :: Software Development :: Build Tools
Requires-Python: >=3.6
License-File: LICENSE
Requires-Dist: PyGithub==2.6.1
Requires-Dist: PyYAML==6.0.2
Requires-Dist: Jinja2==3.1.6
Requires-Dist: rich==14.0.0
Requires-Dist: colorama==0.4.6
Dynamic: author
Dynamic: classifier
Dynamic: description
Dynamic: description-content-type
Dynamic: license
Dynamic: license-file
Dynamic: requires-dist
Dynamic: requires-python
Dynamic: summary
